querystringsafe_base64/__init__.py
querystringsafe_base64-1.2.0.dist-info/AUTHORS.rst
querystringsafe_base64-1.2.0.dist-info/LICENSE
querystringsafe_base64-1.2.0.dist-info/METADATA
querystringsafe_base64-1.2.0.dist-info/WHEEL
querystringsafe_base64-1.2.0.dist-info/top_level.txt
querystringsafe_base64-1.2.0.dist-info/RECORD
