Metadata-Version: 2.1
Name: querystringsafe-base64
Version: 1.2.0
Summary: Encoding and decoding arbitrary strings into strings that are safe to put into a URL query param.
Home-page: https://github.com/ClearcodeHQ/querystringsafe_base64
Author: Clearcode - The A Room
Author-email: thearoom@clearcode.cc
License: LGPL
Platform: UNKNOWN
Classifier: Intended Audience :: Developers
Classifier: Operating System :: OS Independent
Classifier: Natural Language :: English
Classifier: Programming Language :: Python
Classifier: Programming Language :: Python :: 2
Classifier: Programming Language :: Python :: 2.7
Classifier: Programming Language :: Python :: 3
Classifier: Programming Language :: Python :: 3.4
Classifier: Programming Language :: Python :: 3.5
Classifier: Programming Language :: Python :: 3.6
Classifier: License :: OSI Approved :: GNU Lesser General Public License v3 or later (LGPLv3+)
Classifier: Topic :: Software Development :: Libraries :: Python Modules
Classifier: Environment :: Web Environment
Provides-Extra: tests
Requires-Dist: pytest ; extra == 'tests'
Requires-Dist: pytest-cov ; extra == 'tests'
Requires-Dist: pylama ; extra == 'tests'
